doc/the300_helper.py
doc/source/conf.py
pymgal/SSP_models.py
pymgal/__init__.py
pymgal/__version__.py
pymgal/dusts.py
pymgal/filters.py
pymgal/load_data.py
pymgal/mock_observation.py
pymgal/projection.py
pymgal/readsnapsgl.py
pymgal/utils.py
pymgal/filters/2mass_h
pymgal/filters/2mass_j
pymgal/filters/2mass_ks
pymgal/filters/4star_h
pymgal/filters/4star_j
pymgal/filters/4star_ks
pymgal/filters/4star_m_hlong
pymgal/filters/4star_m_hshort
pymgal/filters/4star_m_j1
pymgal/filters/4star_m_j2
pymgal/filters/4star_m_j3
pymgal/filters/README.rst
pymgal/filters/b
pymgal/filters/bessell_l
pymgal/filters/bessell_lp
pymgal/filters/bessell_m
pymgal/filters/buser_b
pymgal/filters/cfht_b
pymgal/filters/cfht_i
pymgal/filters/cfht_r
pymgal/filters/cousins_i
pymgal/filters/cousins_r
pymgal/filters/csst_g
pymgal/filters/csst_i
pymgal/filters/csst_nuv
pymgal/filters/csst_r
pymgal/filters/csst_u
pymgal/filters/csst_y
pymgal/filters/csst_z
pymgal/filters/des_g
pymgal/filters/des_i
pymgal/filters/des_r
pymgal/filters/des_y
pymgal/filters/des_z
pymgal/filters/euclid_h
pymgal/filters/euclid_j
pymgal/filters/euclid_vis
pymgal/filters/euclid_y
pymgal/filters/fors_r
pymgal/filters/fors_v
pymgal/filters/galex_fuv
pymgal/filters/galex_nuv
pymgal/filters/i1500
pymgal/filters/i2300
pymgal/filters/i2800
pymgal/filters/irac_1
pymgal/filters/irac_2
pymgal/filters/irac_3
pymgal/filters/irac_4
pymgal/filters/iras_100
pymgal/filters/iras_12
pymgal/filters/iras_25
pymgal/filters/iras_60
pymgal/filters/isaac_ks
pymgal/filters/jwst_f070w
pymgal/filters/jwst_f090w
pymgal/filters/jwst_f115w
pymgal/filters/jwst_f150w
pymgal/filters/jwst_f200w
pymgal/filters/jwst_f277w
pymgal/filters/jwst_f356w
pymgal/filters/jwst_f444w
pymgal/filters/lsst_g
pymgal/filters/lsst_i
pymgal/filters/lsst_r
pymgal/filters/lsst_u
pymgal/filters/lsst_y
pymgal/filters/lsst_z
pymgal/filters/megacam_g
pymgal/filters/megacam_i
pymgal/filters/megacam_r
pymgal/filters/megacam_u
pymgal/filters/megacam_z
pymgal/filters/mips_160
pymgal-1.0.dist-info/AUTHORS.md
pymgal-1.0.dist-info/LICENSE
pymgal-1.0.dist-info/METADATA
pymgal-1.0.dist-info/WHEEL
pymgal-1.0.dist-info/top_level.txt
pymgal-1.0.dist-info/RECORD
