Metadata-Version: 2.1
Name: pymgal
Version: 1.0
Summary: A Package for Mock Observations in optical bands
Author: Weiguang Cui, Patrick Janulewicz
Author-email: cuiweiguang@gmail.com, patrick.janulewicz@mail.mcgill.ca
License: BSD
Keywords: astronomy astrophysics hydrodynamical simulation mock observation
Classifier: Development Status :: 5 - Production/Stable
Classifier: Intended Audience :: Science/Research
Classifier: Natural Language :: English
Classifier: Topic :: Scientific/Engineering :: Astronomy
Classifier: License :: OSI Approved :: BSD License
Classifier: Programming Language :: Python :: 2
Classifier: Programming Language :: Python :: 3
License-File: LICENSE
License-File: AUTHORS.md
Requires-Dist: astropy>=5.3
Requires-Dist: h5py>=3.7.0
Requires-Dist: numpy<2.1,>=1.23.5
Requires-Dist: PyYAML>=6.0.1
Requires-Dist: scipy>=1.10
Requires-Dist: setuptools>=69.0.3
Requires-Dist: numba>=0.5
